time_split_app/__init__.py
time_split_app/_logging.py
time_split_app/_select_link_impl_from_entrypoint.py
time_split_app/_support.py
time_split_app/_views.py
time_split_app/app.py
time_split_app/cli.py
time_split_app/config.py
time_split_app/datasets/__init__.py
time_split_app/datasets/_config.py
time_split_app/datasets/_datasets.py
time_split_app/datasets/_load.py
time_split_app/datasets/_read_fn.py
time_split_app/formatting.py
time_split_app/new/Dockerfile
time_split_app/new/README.md
time_split_app/new/datasets/covid19.csv
time_split_app/new/datasets/datasets.toml
time_split_app/new/entrypoint.sh
time_split_app/new/extensions/__init__.py
time_split_app/new/extensions/my_dataset_loader.py
time_split_app/new/extensions/my_kwargs_type.py
time_split_app/new/extensions/my_plot_fn.py
time_split_app/new/extensions/my_select_fn.py
time_split_app/new/extensions.env
time_split_app/new/start-dev.sh
time_split_app/py.typed
time_split_app/style.css
time_split_app/style.py
time_split_app/widgets/__init__.py
time_split_app/widgets/data/__init__.py
time_split_app/widgets/data/_data.py
time_split_app/widgets/data/_data_loader_widget.py
time_split_app/widgets/data/_datasets.py
time_split_app/widgets/data/_loader_from_env_entrypoint.py
time_split_app/widgets/data/_sample_data.py
time_split_app/widgets/data/load.py
time_split_app/widgets/data/sample.csv
time_split_app/widgets/display/__init__.py
time_split_app/widgets/display/_aggregate.py
time_split_app/widgets/display/_code.py
time_split_app/widgets/display/_overview.py
time_split_app/widgets/display/_performance.py
time_split_app/widgets/display/_plot_folds.py
time_split_app/widgets/display/_select_impl_from_entrypoint.py
time_split_app/widgets/parameters/__init__.py
time_split_app/widgets/parameters/_expand_limits.py
time_split_app/widgets/parameters/_schedule.py
time_split_app/widgets/parameters/_schedule_filter.py
time_split_app/widgets/parameters/_select_impl_from_entrypoint.py
time_split_app/widgets/parameters/_span.py
time_split_app-2.5.0.dist-info/METADATA
time_split_app-2.5.0.dist-info/WHEEL
time_split_app-2.5.0.dist-info/licenses/LICENSE.md
time_split_app-2.5.0.dist-info/RECORD
