Metadata-Version: 2.4
Name: time-split-app
Version: 2.5.0
Summary: Companion app for the `time-split` library.
License: MIT
License-File: LICENSE.md
Author: Richard Sundqvist
Author-email: richard.sundqvist@live.se
Requires-Python: >=3.11
Classifier: Development Status :: 5 - Production/Stable
Classifier: Intended Audience :: Developers
Classifier: Intended Audience :: Science/Research
Classifier: Operating System :: POSIX :: Linux
Classifier: Operating System :: MacOS
Classifier: Operating System :: Microsoft :: Windows
Classifier: License :: OSI Approved :: MIT License
Classifier: Natural Language :: English
Classifier: Programming Language :: Python :: 3
Classifier: Programming Language :: Python :: 3 :: Only
Classifier: Programming Language :: Python :: 3.11
Classifier: Programming Language :: Python :: 3.12
Classifier: Programming Language :: Python :: 3.13
Classifier: Programming Language :: Python :: 3.14
Requires-Dist: croniter (>=6.0.0)
Requires-Dist: matplotlib
Requires-Dist: pandas (>=2.0.3)
Requires-Dist: rics (>=6.0.2)
Requires-Dist: streamlit (>=1.49.1)
Requires-Dist: time-split[plotting] (>=1.0.0)
Project-URL: Bug Tracker, https://github.com/rsundqvist/time-split-app/issues
Project-URL: Changelog, https://github.com/rsundqvist/time-split-app/blob/master/CHANGELOG.md
Project-URL: Documentation, https://time-fold.readthedocs.io
Project-URL: Homepage, https://github.com/rsundqvist/time-split-app
Project-URL: Repository, https://github.com/rsundqvist/time-split-app
